egon/__init__.py
egon/connectors.py
egon/decorators.py
egon/exceptions.py
egon/mock.py
egon/multiprocessing.py
egon/nodes.py
egon/pipeline.py
egon/utils.py
egon/visualize/__init__.py
egon/visualize/callbacks.py
egon/visualize/assets/cyto_style.yml
egon/visualize/assets/favicon.ico
egon/visualize/assets/style.css
egon/visualize/components/__init__.py
egon/visualize/components/custom.py
egon/visualize/components/cyto.py
egon/visualize/components/graphs.py
tests/__init__.py
tests/test_decorators.py
tests/test_connectors/__init__.py
tests/test_connectors/test_base_connector.py
tests/test_connectors/test_input.py
tests/test_connectors/test_multi_partner_support.py
tests/test_connectors/test_output.py
tests/test_multiprocessing/__init__.py
tests/test_multiprocessing/test_mpool.py
tests/test_nodes/__init__.py
tests/test_nodes/test_abstract_node.py
tests/test_nodes/test_node_validation.py
tests/test_pipeline/__init__.py
tests/test_pipeline/test_linear_pipeline.py
tests/test_pipeline/test_pipeline.py
tests/test_utils/__init__.py
tests/test_utils/test_collection.py
egon-0.6.1.dist-info/METADATA
egon-0.6.1.dist-info/WHEEL
egon-0.6.1.dist-info/top_level.txt
egon-0.6.1.dist-info/RECORD
