Metadata-Version: 2.1
Name: egon
Version: 0.6.1
Summary: A lightweight, minimalist framework for the rapid development of analysis pipelines.
Home-page: UNKNOWN
Author: MWV Research Group
License: GPL v3
Keywords: Data Pipeline Parallel Pipeline
Platform: UNKNOWN
Classifier: License :: OSI Approved :: GNU General Public License v3 or later (GPLv3+)
Classifier: Natural Language :: English
Classifier: Operating System :: OS Independent
Classifier: Programming Language :: Python
Requires-Python: >=3.6
Requires-Dist: boltons (>=20.2.1)
Requires-Dist: dash (>=1.20.0)
Requires-Dist: dash-cytoscape (>=0.2.0)
Requires-Dist: pyyaml (>=5.4.1)
Requires-Dist: pandas
Requires-Dist: plotly (>=4.14.3)
Requires-Dist: psutil (>=5.8.0)
Requires-Dist: numpy (>=1.20.1)
Requires-Dist: setuptools (>=51.0.0)
Requires-Dist: waitress
